Automated/Automated_cartography.py
Automated/__init__.py
LSC_Client/LSC_Client.py
LSC_Client/__init__.py
ddm_robot/LSC_Client.py
ddm_robot/__init__.py
ddm_robot/ddm_robot.py
ddm_robot/robot.py
ddm_robot/showlib.py
ddm_robot/voice.py
example/__init__.py
example/f1.py
example/f2.py
robot/LSC_Client.py
robot/__init__.py
robot/comment.py
robot/get_ip.py
robot/lsc.py
robot/makeros.py
robot/robot.py
robot/shortshow.py
robot/showlib.py
robot/voice.py
Automated_cartography-0.0.2.dist-info/METADATA
Automated_cartography-0.0.2.dist-info/WHEEL
Automated_cartography-0.0.2.dist-info/top_level.txt
Automated_cartography-0.0.2.dist-info/RECORD
