Metadata-Version: 2.1
Name: Automated-cartography
Version: 0.0.2
Summary: This is a package for Excel Chart Standard Production Library
Home-page: https://github.com/NocoldBob/Automated_cartography
Author: fastbiubiu
Author-email: fastbiubiu@163.com
License: UNKNOWN
Platform: UNKNOWN
Classifier: Programming Language :: Python :: 3
Classifier: License :: OSI Approved :: MIT License
Classifier: Operating System :: OS Independent
